ctranslate2-4.6.3.dist-info/RECORD
ctranslate2-4.6.3.dist-info/WHEEL
ctranslate2-4.6.3.dist-info/entry_points.txt
ctranslate2-4.6.3.dist-info/top_level.txt
ctranslate2-4.6.3.dist-info/METADATA
ctranslate2/logging.py
ctranslate2/version.py
ctranslate2/__init__.py
ctranslate2/extensions.py
ctranslate2/_ext.cpython-314-darwin.so
ctranslate2/specs/model_spec.py
ctranslate2/specs/transformer_spec.py
ctranslate2/specs/wav2vec2bert_spec.py
ctranslate2/specs/common_spec.py
ctranslate2/specs/__init__.py
ctranslate2/specs/attention_spec.py
ctranslate2/specs/wav2vec2_spec.py
ctranslate2/specs/whisper_spec.py
ctranslate2/converters/opennmt_tf.py
ctranslate2/converters/fairseq.py
ctranslate2/converters/transformers.py
ctranslate2/converters/opus_mt.py
ctranslate2/converters/converter.py
ctranslate2/converters/__init__.py
ctranslate2/converters/marian.py
ctranslate2/converters/utils.py
ctranslate2/converters/eole_ct2.py
ctranslate2/converters/opennmt_py.py
ctranslate2/converters/openai_gpt2.py
ctranslate2/models/__init__.py
ctranslate2/.dylibs/libiomp5.dylib
ctranslate2/.dylibs/libctranslate2.4.6.3.dylib
